gtkpass/__init__.py
gtkpass/main.py
gtkpass-0.2.6.dist-info/DESCRIPTION.rst
gtkpass-0.2.6.dist-info/METADATA
gtkpass-0.2.6.dist-info/RECORD
gtkpass-0.2.6.dist-info/WHEEL
gtkpass-0.2.6.dist-info/entry_points.txt
gtkpass-0.2.6.dist-info/metadata.json
gtkpass-0.2.6.dist-info/top_level.txt
