Metadata-Version: 2.0
Name: gtkpass
Version: 0.2.6
Summary: A GTK+ 3 program for the standard unix password manager
Home-page: http://github.com/raghavsub/gtkpass
Author: Raghav Subramaniam
Author-email: raghavs511@gmail.com
License: MIT
Platform: UNKNOWN
